nvboard/RTL_prj/prj_3/vsrc/light.v
module light (
    input clk,input rst,output reg [15:0] led);
    reg[31:0] count;
    always @(posedge clk) begin
        if (rst) begin
            led <= 1;
            count <= 0;
        end else begin
            if (count == 0) 
            led <={led[14:0],led[15]};
            count <=(count >= 500000 ? 32'b0 : count +1);
// 实现一个模500000的计数器，用于产生一个周期为500000个时钟周期的使能信号，控制LED每隔500000个时钟周期移位一次
        end
    end
endmodule

nvboard/RTL_prj/p2_light/sim_obj/light.vcd
$version Generated by VerilatedVcd $end
$timescale 1ps $end
 $scope module TOP $end
  $var wire 1 # clk $end
  $var wire 1 $ rst $end
  $var wire 16 % led [15:0] $end
  $scope module light $end
   $var wire 1 # clk $end
   $var wire 1 $ rst $end
   $var wire 16 % led [15:0] $end
   $var wire 32 & count [31:0] $end
  $upscope $end
 $upscope $end
$enddefinitions $end


#0
0#
1$
b0000000000000000 %
b00000000000000000000000000000000 &
#10
1#
b0000000000000001 %
#20
0#
#30
1#
#40
0#
#50
1#
#60
0#
#70
1#
#80
0#
#90
1#
#100
0#
#110
1#
#120
0#
#130
1#
#140
0#
#150
1#
#160
0#
#170
1#
#180
0#
#190
1#
#200
0#
0$
#210
1#
b0000000000000010 %
#220
0#
#230
1#
b0000000000000100 %
#240
0#
#250
1#
b0000000000001000 %
#260
0#
#270
1#
b0000000000010000 %
#280
0#
#290
1#
b0000000000100000 %
#300
0#
#310
1#
b0000000001000000 %
#320
0#
#330
1#
b0000000010000000 %
#340
0#
#350
1#
b0000000100000000 %
#360
0#
#370
1#
b0000001000000000 %
#380
0#
#390
1#
b0000010000000000 %
#400
0#
#410
1#
b0000100000000000 %
#420
0#
#430
1#
b0001000000000000 %
#440
0#
#450
1#
b0010000000000000 %
#460
0#
#470
1#
b0100000000000000 %
#480
0#
#490
1#
b1000000000000000 %
#500
0#
#510
1#
b0000000000000001 %
#520
0#
#530
1#
b0000000000000010 %
#540
0#
#550
1#
b0000000000000100 %
#560
0#
#570
1#
b0000000000001000 %
#580
0#
#590
1#
b0000000000010000 %
#600
0#
#610
1#
b0000000000100000 %
#620
0#
#630
1#
b0000000001000000 %
#640
0#
#650
1#
b0000000010000000 %
#660
0#
#670
1#
b0000000100000000 %
#680
0#
#690
1#
b0000001000000000 %
#700
0#
#710
1#
b0000010000000000 %
#720
0#
#730
1#
b0000100000000000 %
#740
0#
#750
1#
b0001000000000000 %
#760
0#
#770
1#
b0010000000000000 %
#780
0#
#790
1#
b0100000000000000 %
#800
0#
#810
1#
b1000000000000000 %
#820
0#
#830
1#
b0000000000000001 %
#840
0#
#850
1#
b0000000000000010 %
#860
0#
#870
1#
b0000000000000100 %
#880
0#
#890
1#
b0000000000001000 %
#900
0#
#910
1#
b0000000000010000 %
#920
0#
#930
1#
b0000000000100000 %
#940
0#
#950
1#
b0000000001000000 %
#960
0#
#970
1#
b0000000010000000 %
#980
0#
#990
1#
b0000000100000000 %
#1000
0#
#1010
1#
b0000001000000000 %
#1020
0#
#1030
1#
b0000010000000000 %
#1040
0#
#1050
1#
b0000100000000000 %
#1060
0#
#1070
1#
b0001000000000000 %
#1080
0#
#1090
1#
b0010000000000000 %
#1100
0#
#1110
1#
b0100000000000000 %
#1120
0#
#1130
1#
b1000000000000000 %
#1140
0#
#1150
1#
b0000000000000001 %
#1160
0#
#1170
1#
b0000000000000010 %
#1180
0#
#1190
1#
b0000000000000100 %
#1200
0#
#1210
1#
b0000000000001000 %
#1220
0#
#1230
1#
b0000000000010000 %
#1240
0#
#1250
1#
b0000000000100000 %
#1260
0#
#1270
1#
b0000000001000000 %
#1280
0#
#1290
1#
b0000000010000000 %
#1300
0#
#1310
1#
b0000000100000000 %
#1320
0#
#1330
1#
b0000001000000000 %
#1340
0#
#1350
1#
b0000010000000000 %
#1360
0#
#1370
1#
b0000100000000000 %
#1380
0#
#1390
1#
b0001000000000000 %
#1400
0#
#1410
1#
b0010000000000000 %
#1420
0#
#1430
1#
b0100000000000000 %
#1440
0#
#1450
1#
b1000000000000000 %
#1460
0#
#1470
1#
b0000000000000001 %
#1480
0#
#1490
1#
b0000000000000010 %
#1500
0#
#1510
1#
b0000000000000100 %
#1520
0#
#1530
1#
b0000000000001000 %
#1540
0#
#1550
1#
b0000000000010000 %
#1560
0#
#1570
1#
b0000000000100000 %
#1580
0#
#1590
1#
b0000000001000000 %
#1600
0#
#1610
1#
b0000000010000000 %
#1620
0#
#1630
1#
b0000000100000000 %
#1640
0#
#1650
1#
b0000001000000000 %
#1660
0#
#1670
1#
b0000010000000000 %
#1680
0#
#1690
1#
b0000100000000000 %
#1700
0#
#1710
1#
b0001000000000000 %
#1720
0#
#1730
1#
b0010000000000000 %
#1740
0#
#1750
1#
b0100000000000000 %
#1760
0#
#1770
1#
b1000000000000000 %
#1780
0#
#1790
1#
b0000000000000001 %
#1800
0#
#1810
1#
b0000000000000010 %
#1820
0#
#1830
1#
b0000000000000100 %
#1840
0#
#1850
1#
b0000000000001000 %
#1860
0#
#1870
1#
b0000000000010000 %
#1880
0#
#1890
1#
b0000000000100000 %
#1900
0#
#1910
1#
b0000000001000000 %
#1920
0#
#1930
1#
b0000000010000000 %
#1940
0#
#1950
1#
b0000000100000000 %
#1960
0#
#1970
1#
b0000001000000000 %
#1980
0#
#1990
1#
b0000010000000000 %
#2000
0#
#2010
1#
b0000100000000000 %
#2020
0#
#2030
1#
b0001000000000000 %
#2040
0#
#2050
1#
b0010000000000000 %
#2060
0#
#2070
1#
b0100000000000000 %
#2080
0#
#2090
1#
b1000000000000000 %
#2100
0#
#2110
1#
b0000000000000001 %
#2120
0#
#2130
1#
b0000000000000010 %
#2140
0#
#2150
1#
b0000000000000100 %
#2160
0#
#2170
1#
b0000000000001000 %
#2180
0#
#2190
1#
b0000000000010000 %
