nvboard/RTL_prj/p3_mux2_1/vsrc/mux2_1.v
/********二选一多路选择器****************
    s=0,y=a;
    s=1,y=b;
法一：三目条件运算法：
**************************************/

module mux2_1 (
    input a,b,s,
    output y
);
    assign y= (s == 1'b0) ? a : b;
endmodule

/* 法二：数据流 assign  
module mux2_1 (
    input a,b,s,
    output y
);
    assign y = (~s&a) | (s&b);
endmodule
*/

/* 法三：always中使用：if -else 
module mux2_1 (
    input a,b,s,
    output reg y
);
    always(*)
        if(s == 1'b0)
            begin y = a;end
        else 
            begin y = b;end

endmodule
*/

/* 法四：always中使用：case-default
module mux2_1 (
    input a,b,s,
    output reg y
);
    always(*)
        begin
            case(s)
            1'b0 : y = a;
            1'b1 : y = b;
            default : y = 1'b0;
            endcase
        end
endmodule
*/

nvboard/RTL_prj/p3_mux2_1/sim_obj/mux2_1.vcd
$version Generated by VerilatedVcd $end
$timescale 1ps $end
 $scope module TOP $end
  $var wire 1 # a $end
  $var wire 1 $ b $end
  $var wire 1 % s $end
  $var wire 1 & y $end
  $scope module mux2_1 $end
   $var wire 1 # a $end
   $var wire 1 $ b $end
   $var wire 1 % s $end
   $var wire 1 & y $end
  $upscope $end
 $upscope $end
$enddefinitions $end


#0
0#
1$
1%
1&
#10
1#
#20
0#
0%
0&
#30
1%
1&
#40
1#
0%
#50
0#
0$
0&
#60
1$
#70
1#
1&
#80
0#
0$
0&
#90
1#
1$
1%
1&
#100
0#
0$
0&
#110
1#
1$
0%
1&
#120
0#
1%
#130
1#
0%
#140
0$
1%
0&
#150
0#
#160
1$
1&
#170
1#
0$
0%
#190
0#
1$
0&
#200
1#
0$
1%
#210
0#
1$
1&
#220
1#
0%
#230
0#
1%
#240
1#
0$
0%
#250
0#
1%
0&
#260
1$
1&
#270
0$
0%
0&
#280
1$
#290
1%
1&
#300
0$
0%
0&
#310
1#
1&
#320
0#
0&
#330
1#
1%
#340
0#
1$
0%
#350
1#
0$
1%
#360
0#
#370
1#
0%
1&
#380
1$
#390
0#
1%
#400
1#
0%
#410
1%
#430
0$
0&
#450
0#
1$
1&
#460
0$
0&
#470
1$
1&
#480
1#
0$
0&
#490
0#
1$
0%
